MANIFEST.in
README.md
setup.py
salesforce_analytics/__init__.py
salesforce_analytics.egg-info/PKG-INFO
salesforce_analytics.egg-info/SOURCES.txt
salesforce_analytics.egg-info/dependency_links.txt
salesforce_analytics.egg-info/not-zip-safe
salesforce_analytics.egg-info/top_level.txt