Metadata-Version: 1.1
Name: salesforce-analytics
Version: 0.1.3rc0
Summary: Client to injest SalesForce Case information and generate
Home-page: https://github.com/iamjohnnym/salesforce-analytics.git
Author: John Martin
Author-email: john.martin@configure.systems
License: MIT
Keywords: salesforce analytics libary
Platform: UNKNOWN
Classifier: Development Status :: 3 - Alpha
Classifier: License :: OSI Approved :: MIT License
Classifier: Programming Language :: Python :: 2.7
Classifier: Topic :: Text Processing :: Linguistic
